setup.py
pulumi_splight/__init__.py
pulumi_splight/_inputs.py
pulumi_splight/_utilities.py
pulumi_splight/action.py
pulumi_splight/alert.py
pulumi_splight/algorithm.py
pulumi_splight/asset.py
pulumi_splight/asset_attribute.py
pulumi_splight/asset_metadata.py
pulumi_splight/asset_relation.py
pulumi_splight/bus.py
pulumi_splight/command.py
pulumi_splight/component.py
pulumi_splight/component_routine.py
pulumi_splight/connector.py
pulumi_splight/dashboard.py
pulumi_splight/dashboard_actionlist_chart.py
pulumi_splight/dashboard_alertevents_chart.py
pulumi_splight/dashboard_alertlist_chart.py
pulumi_splight/dashboard_assetlist_chart.py
pulumi_splight/dashboard_bar_chart.py
pulumi_splight/dashboard_bargauge_chart.py
pulumi_splight/dashboard_commandlist_chart.py
pulumi_splight/dashboard_gauge_chart.py
pulumi_splight/dashboard_histogram_chart.py
pulumi_splight/dashboard_image_chart.py
pulumi_splight/dashboard_stat_chart.py
pulumi_splight/dashboard_tab.py
pulumi_splight/dashboard_table_chart.py
pulumi_splight/dashboard_text_chart.py
pulumi_splight/dashboard_timeseries_chart.py
pulumi_splight/external_grid.py
pulumi_splight/file.py
pulumi_splight/file_folder.py
pulumi_splight/function.py
pulumi_splight/generator.py
pulumi_splight/get_asset_kinds.py
pulumi_splight/get_buses.py
pulumi_splight/get_generators.py
pulumi_splight/get_grids.py
pulumi_splight/get_lines.py
pulumi_splight/get_tags.py
pulumi_splight/grid.py
pulumi_splight/inverter.py
pulumi_splight/line.py
pulumi_splight/node.py
pulumi_splight/outputs.py
pulumi_splight/provider.py
pulumi_splight/pulumi-plugin.json
pulumi_splight/py.typed
pulumi_splight/secret.py
pulumi_splight/segment.py
pulumi_splight/server.py
pulumi_splight/slack_generator.py
pulumi_splight/slack_line.py
pulumi_splight/tag.py
pulumi_splight/transformer.py
pulumi_splight.egg-info/PKG-INFO
pulumi_splight.egg-info/SOURCES.txt
pulumi_splight.egg-info/dependency_links.txt
pulumi_splight.egg-info/not-zip-safe
pulumi_splight.egg-info/requires.txt
pulumi_splight.egg-info/top_level.txt
pulumi_splight/config/__init__.py
pulumi_splight/config/vars.py