Metadata-Version: 2.1
Name: pulumi-splight
Version: 1.2.18
Summary: A Pulumi package for creating and managing Splight resources.
Home-page: https://www.splight-ai.com
License: Apache-2.0
Project-URL: Repository, https://github.com/splightplatform/pulumi-splight
Keywords: splightplatform splight infrastructure
Platform: UNKNOWN
Requires-Python: >=3.8
